pyqt_ani_radiobutton/__init__.py
pyqt_ani_radiobutton/aniRadioButton.py
pyqt_ani_radiobutton-0.0.1.dist-info/LICENSE
pyqt_ani_radiobutton-0.0.1.dist-info/METADATA
pyqt_ani_radiobutton-0.0.1.dist-info/WHEEL
pyqt_ani_radiobutton-0.0.1.dist-info/top_level.txt
pyqt_ani_radiobutton-0.0.1.dist-info/RECORD
