Metadata-Version: 2.1
Name: pyqt-ani-radiobutton
Version: 0.0.1
Summary: PyQt animated QRadioButton
Home-page: https://github.com/yjg30737/pyqt-ani-radiobutton.git
Author: Jung Gyu Yoon
Author-email: yjg30737@gmail.com
License: MIT
Platform: UNKNOWN
License-File: LICENSE
Requires-Dist: PyQt5 (>=5.8)
Requires-Dist: pyqt-ani-abstractbutton (>=0.0.1)
